hmr_daemon-0.4.2.1.dist-info/METADATA
hmr_daemon-0.4.2.1.dist-info/WHEEL
hmr_daemon-0.4.2.1.dist-info/entry_points.txt
hmr_daemon/__init__.py
hmr_daemon/posix/__init__.py
hmr_daemon/posix/main.py
hmr_daemon/posix/worker.py
hmr_daemon/windows.py
hmr_daemon_.pth
hmr_daemon-0.4.2.1.dist-info/RECORD
