Metadata-Version: 2.1
Name: hmr-daemon
Version: 0.4.2.1
Project-URL: Homepage, https://github.com/promplate/hmr
Requires-Dist: hmr<0.8,>=0.5.0
